_tcore/fp4_to_fp9fp4.v
module fp4_to_fp9 (
	input	wire[7:0]	packed_fp4,
	input	wire		select_high,
	output	reg[8:0]	fp9,
	output	reg		invalid,
	output	reg		underflow,
	output	reg		overflow
);
always @(*) begin

        reg	[3:0]	fp4_high;
		reg	[3:0]	fp4_low;

		reg	[3:0]	selected_fp4;

		reg		fp4_sgn;
		reg	[1:0]	fp4_exp;
		reg		fp4_sig;	
	fp9 = 9'h0;
	invalid = 1'b0;
	underflow = 1'b0;
	overflow = 1'b0;

	fp4_high = packed_fp4[7:4];
	fp4_low = packed_fp4[3:0];
	selected_fp4 = select_high ? fp4_high : fp4_low;
	fp4_sgn = selected_fp4[3];
	fp4_exp = selected_fp4[2:1];
	fp4_sig = selected_fp4[0];

//check NaN & Inf
	if(fp4_exp == 2'b11) begin
	  if(fp4_sig == 1'b1) begin
		//NaN
		//fp9 = {fp4_sgn, 4'b1111, 4'b0001};
		fp9 = {fp4_sgn, 5'b11111, 3'b001};
		invalid = 1'b1;
	  end else begin
		//Inf
		fp9 = {fp4_sgn, 5'b11111, 3'b000};
	  end
	end
//check zero
	else if (fp4_exp == 2'b00) begin
	if (fp4_sig == 1'b0) begin
		fp9 = {fp4_sgn, 5'b00000, 3'b000};
	end else begin
	//fp9={fp4_sgn,5'b00001,3'b000};
	fp9={fp4_sgn,5'b00000,{fp4_sig,2'b00}};
	end
	end
	else begin
		case(fp4_exp)
		  2'b00:begin
			fp9[8] = fp4_sgn;
			fp9[7:3] = 5'b00000;
			fp9[2:0] = {fp4_sig,2'b00};
		  end
		  2'b01:begin
			fp9[8] = fp4_sgn;
			fp9[7:3] = 5'b01111; //1+6=7
			fp9[2:0] = {fp4_sig,2'b00};
		  end
		  2'b10:begin
			//fp9[8] = fp4_sgn;
			//fp9[7:3] = 5'b10000; //2+6=8
			//fp9[2:0] = {fp4_sig, 2'b00};
			fp9 = {fp4_sgn,5'b11111,3'b000};
		  end
		  default:begin
			fp9 = {fp4_sgn,5'b11111,3'b000};
			
		  end
		endcase
	end

end
endmodule

_tcore/tb_fp4_to_fp9.v

module tb_fp4_to_fp9;
	reg [7:0]	packed_fp4;
	reg		select_high;
	wire [8:0]	fp9;
	wire		invalid,underflow,overflow;
    reg [7:0]	test_cases [0:19];
	reg [8:0]	expected_results [0:19];
	reg [2:0]	expected_flags [0:19];
	reg 		expected_select[0:19];
	fp4_to_fp9 uut(
		.packed_fp4(packed_fp4),
		.fp9(fp9),
		.select_high(select_high),
		.invalid(invalid),
		.underflow(underflow),
		.overflow(overflow)
);
	

	integer		i;
	integer		error_count;
	initial	begin
		initialize_test_cases();
		error_count = 0;

		for (i=0;i<20;i=i+1) begin
			packed_fp4 = test_cases[i];
			select_high = expected_select[i];
			#10;
			check_result(i);
		end
    
		$display("Test Summary:");
		$display("Total test cases:%0d",20);
		$display("Errors:%0d",error_count);

		if(error_count == 0) begin
			$display("All tests passed!");
		end else begin
			$display("Some tests failed!");
		end
		#10;
		$finish;
	end

	task initialize_test_cases;
		begin
			test_cases[0] = 8'h00;
			expected_select[0] = 1'b0;		
			expected_results[0] = 9'h000;
			expected_flags[0] = 3'b000;

			test_cases[1] = 8'h00;
			expected_select[1] = 1'b1;
			expected_results[1] = 9'h000;
			expected_flags[1] = 3'b000;

			test_cases[2] = 8'h80;
			expected_select[2] = 1'b1;
			expected_results[2] = 9'h100;
			expected_flags[2] = 3'b000;

			test_cases[3] = 8'h80;
			expected_select[3] = 1'b1;
			expected_results[3] = 9'h100;
			expected_flags[3] = 3'b000;

			test_cases[4] = 8'h51;
			expected_select[4] = 1'b0;
			expected_results[4] = 9'h008;
			expected_flags[4] = 3'b000;

			test_cases[5] = 8'h51;
			expected_select[5] = 1'b1;
			expected_results[5] = 9'h0F8;
			expected_flags[5] = 3'b000;

			test_cases[6] = 8'h84;
			expected_select[6] = 1'b0;
			expected_results[6] = 9'h0f8;
			expected_flags[6] = 3'b000;

			test_cases[7] = 8'h84;
			expected_select[7] = 1'b1;
			expected_results[7] = 9'h100;
			expected_flags[7] = 3'b000;

			test_cases[8] = 8'h21;
			expected_select[8] = 1'b0;
			expected_results[8] = 9'h008;
			expected_flags[8] = 3'b000;

			test_cases[9] = 8'h21;
			expected_select[9] = 1'b1;
			expected_results[9] = 9'h078;
			expected_flags[9] = 3'b000;

			test_cases[10] = 8'hE0;
			expected_select[10] = 1'b0;
			expected_results[10] = 9'h000;
			expected_flags[10] = 3'b000;

			test_cases[11] = 8'hE0;
			expected_select[11] = 1'b1;
			expected_results[11] = 9'h1f8;
			expected_flags[11] = 3'b000;

			test_cases[12] = 8'hF0;
			expected_select[12] = 1'b0;
			expected_results[12] = 9'h000;
			expected_flags[12] = 3'b000;

			test_cases[13] = 8'hF0;
			expected_select[13] = 1'b1;
			expected_results[13] = 9'h1F9;
			expected_flags[13] = 3'b100;

			test_cases[14] = 8'hF2;
			expected_select[14] = 1'b0;
			expected_results[14] = 9'h078;
			expected_flags[14] = 3'b000;

			test_cases[15] = 8'hF2;
			expected_select[15] = 1'b1;
			expected_results[15] = 9'h1F9;
			expected_flags[15] = 3'b100;

			test_cases[16] = 8'h3C;
			expected_select[16] = 1'b0;
			expected_results[16] = 9'h1f8;
			expected_flags[16] = 3'b000;

			test_cases[17] = 8'h3C;
			expected_select[17] = 1'b1;
			expected_results[17] = 9'h07c;
			expected_flags[17] = 3'b000;

			test_cases[18] = 8'hB3;
			expected_select[18] = 1'b0;
			expected_results[18] = 9'h07C;
			expected_flags[18] = 3'b000;

			test_cases[19] = 8'hA2;
			expected_select[19] = 1'b1;
			expected_results[19] = 9'h178;
			expected_flags[19] = 3'b000;
		end
	endtask
	
	task check_result;
		input integer test_num;
		reg pass;
		begin
			pass = 1;
			if(fp9 !== expected_results[test_num]) begin
                        pass = 0;
			$display("ERROR:FP9 mismatch");
                        $display("Error at time %t:[Test %d] FP9 MISMATCH!",$time,test_num);
                        $display(" -> Expected FP9: 9'h%h",expected_results[test_num]);
                        $display(" -> Actual FP9: 9'h%h",fp9);
			end

			if({invalid,underflow,overflow} !== expected_flags[test_num]) begin
			pass = 0;
			$display("ERROR:Flags mismatch");
                        $display("Error at time %t:[Test %d] FLAGS MISMATCH!",$time,test_num);
                        $display(" -> Expected Flags: 3'b%b",expected_flags[test_num]);
                      	
			end

			if(!pass) begin
			error_count = error_count + 1;
			//$display("Expected flags:%b",expected_flags[test_num]);
                        
			end else begin
			$display("PASS: [Test %d]",test_num);
			end
		end
	endtask
	
	initial begin
		$dumpfile("fp4_to_fp9.vcd");
		$fsdbDumpfile("fp4_to_fp9.fsdb");
		$fsdbDumpvars("+all",tb_fp4_to_fp9);
	end

endmodule

_tcore/fp4_to_fp9.vcd
$date
	Fri Nov  7 16:17:42 2025
$end

$version
	Synopsys VCS version O-2018.09-SP2_Full64
$end

$timescale
	1s
$end

$comment Csum: 1 00305c20f84e0afd $end


$scope module tb_fp4_to_fp9 $end
$var reg 8 ! packed_fp4 [7:0] $end
$var reg 1 " select_high $end
$var wire 9 # fp9 [8:0] $end
$var wire 1 $ invalid $end
$var wire 1 % underflow $end
$var wire 1 & overflow $end
$var integer 32 ' i $end
$var integer 32 ( error_count $end

$scope task initialize_test_cases $end
$upscope $end


$scope task check_result $end
$var integer 32 ) test_num $end
$var reg 1 * pass $end
$upscope $end


$scope module uut $end
$var wire 8 + packed_fp4 [7:0] $end
$var wire 1 , select_high $end
$var reg 9 - fp9 [8:0] $end
$var reg 1 . invalid $end
$var reg 1 / underflow $end
$var reg 1 0 overflow $end

$scope begin unnamed$$_0 $end
$var reg 4 1 fp4_high [3:0] $end
$var reg 4 2 fp4_low [3:0] $end
$var reg 4 3 selected_fp4 [3:0] $end
$var reg 1 4 fp4_sgn $end
$var reg 2 5 fp4_exp [1:0] $end
$var reg 1 6 fp4_sig $end
$upscope $end

$upscope $end

$upscope $end

$enddefinitions $end

#0
$dumpvars
x*
0$
0&
0"
0%
04
06
0.
00
0,
0/
bxxxxxxxxxxxxxxxxxxxxxxxxxxxxxxxx )
b00000000000000000000000000000000 (
b000000000 #
b00000000000000000000000000000000 '
b00000000 !
b00 5
b0000 1
b0000 2
b0000 3
b000000000 -
b00000000 +
$end
#10
b00000000000000000000000000000000 )
1*
b00000000000000000000000000000001 '
1"
1,
#20
b00000000000000000000000000000001 )
b00000000000000000000000000000010 '
b10000000 !
b10000000 +
14
b1000 3
b1000 1
b100000000 -
b100000000 #
#30
b00000000000000000000000000000010 )
b00000000000000000000000000000011 '
#40
b00000000000000000000000000000011 )
b00000000000000000000000000000100 '
b01010001 !
b01010001 +
0"
0,
16
04
b0001 3
b0001 2
b0101 1
b000001000 -
b000001000 #
#50
b00000000000000000000000000000100 )
b00000000000000000000000000000101 '
1"
1,
b10 5
b0101 3
b011111000 -
b011111000 #
#60
b00000000000000000000000000000101 )
b00000000000000000000000000000110 '
b10000100 !
b10000100 +
0"
0,
06
b0100 3
b0100 2
b1000 1
#70
b00000000000000000000000000000110 )
b00000000000000000000000000000111 '
1"
1,
b00 5
14
b1000 3
b100000000 -
b100000000 #
#80
b00000000000000000000000000000111 )
b00000000000000000000000000001000 '
b00100001 !
b00100001 +
0"
0,
16
04
b0001 3
b0001 2
b0010 1
b000001000 -
b000001000 #
#90
b00000000000000000000000000001000 )
b00000000000000000000000000001001 '
1"
1,
06
b01 5
b0010 3
b001111000 -
b001111000 #
#100
b00000000000000000000000000001001 )
b00000000000000000000000000001010 '
b11100000 !
b11100000 +
0"
0,
b00 5
b0000 3
b0000 2
b1110 1
b000000000 -
b000000000 #
#110
b00000000000000000000000000001010 )
b00000000000000000000000000001011 '
1"
1,
b11 5
14
b1110 3
b111111000 -
b111111000 #
#120
b00000000000000000000000000001011 )
b00000000000000000000000000001100 '
b11110000 !
b11110000 +
0"
0,
b00 5
04
b0000 3
b1111 1
b000000000 -
b000000000 #
#130
b00000000000000000000000000001100 )
b00000000000000000000000000001101 '
1"
1,
16
b11 5
14
b1111 3
1.
1$
b111111001 -
b111111001 #
#140
b00000000000000000000000000001101 )
b00000000000000000000000000001110 '
b11110010 !
b11110010 +
0"
0,
06
b01 5
04
b0010 3
b0010 2
0.
0$
b001111000 -
b001111000 #
#150
b00000000000000000000000000001110 )
b00000000000000000000000000001111 '
1"
1,
16
b11 5
14
b1111 3
1.
1$
b111111001 -
b111111001 #
#160
b00000000000000000000000000001111 )
b00000000000000000000000000010000 '
b00111100 !
b00111100 +
0"
0,
06
b10 5
b1100 3
b1100 2
b0011 1
0.
0$
b111111000 -
b111111000 #
#170
b00000000000000000000000000010000 )
b00000000000000000000000000010001 '
1"
1,
16
b01 5
04
b0011 3
b001111100 -
b001111100 #
#180
b00000000000000000000000000010001 )
b00000000000000000000000000010010 '
b10110011 !
b10110011 +
0"
0,
b0011 2
b1011 1
#190
b00000000000000000000000000010010 )
b00000000000000000000000000010011 '
b10100010 !
b10100010 +
1"
1,
06
14
b1010 3
b0010 2
b1010 1
b101111000 -
b101111000 #
#200
b00000000000000000000000000010011 )
b00000000000000000000000000010100 '
